verizon5gmecvnspapi/__init__.py
verizon5gmecvnspapi/api_helper.py
verizon5gmecvnspapi/configuration.py
verizon5gmecvnspapi/verizon_5_gmecvnspapi_client.py
verizon5gmecvnspapi/controllers/__init__.py
verizon5gmecvnspapi/controllers/base_controller.py
verizon5gmecvnspapi/controllers/csp_profiles_controller.py
verizon5gmecvnspapi/controllers/o_auth_authorization_controller.py
verizon5gmecvnspapi/controllers/repositories_controller.py
verizon5gmecvnspapi/controllers/service_claims_controller.py
verizon5gmecvnspapi/controllers/service_metadata_controller.py
verizon5gmecvnspapi/controllers/service_onboarding_controller.py
verizon5gmecvnspapi/exceptions/__init__.py
verizon5gmecvnspapi/exceptions/api_exception.py
verizon5gmecvnspapi/exceptions/edge_service_onboarding_result_error_exception.py
verizon5gmecvnspapi/exceptions/o_auth_provider_exception.py
verizon5gmecvnspapi/http/__init__.py
verizon5gmecvnspapi/http/http_call_back.py
verizon5gmecvnspapi/http/http_method_enum.py
verizon5gmecvnspapi/http/http_request.py
verizon5gmecvnspapi/http/http_response.py
verizon5gmecvnspapi/http/auth/__init__.py
verizon5gmecvnspapi/http/auth/o_auth_2.py
verizon5gmecvnspapi/models/__init__.py
verizon5gmecvnspapi/models/associate_cloud_credential_result.py
verizon5gmecvnspapi/models/aws_csp_profile.py
verizon5gmecvnspapi/models/aws_csp_profile_cred_type_enum.py
verizon5gmecvnspapi/models/azure_csp_profile.py
verizon5gmecvnspapi/models/boundary.py
verizon5gmecvnspapi/models/category.py
verizon5gmecvnspapi/models/category_list.py
verizon5gmecvnspapi/models/category_type_enum.py
verizon5gmecvnspapi/models/claim.py
verizon5gmecvnspapi/models/claim_status_enum.py
verizon5gmecvnspapi/models/claim_status_request.py
verizon5gmecvnspapi/models/claim_type_enum.py
verizon5gmecvnspapi/models/cluster_info_details.py
verizon5gmecvnspapi/models/compatibility.py
verizon5gmecvnspapi/models/csp_compatibility_enum.py
verizon5gmecvnspapi/models/csp_profile.py
verizon5gmecvnspapi/models/csp_profile_data.py
Apiamtic_python-1.6.9.dist-info/LICENSE
Apiamtic_python-1.6.9.dist-info/METADATA
Apiamtic_python-1.6.9.dist-info/WHEEL
Apiamtic_python-1.6.9.dist-info/top_level.txt
Apiamtic_python-1.6.9.dist-info/RECORD
